README.md
setup.py
percentum/__init__.py
percentum/cli.py
percentum/percentum.py
percentum.egg-info/PKG-INFO
percentum.egg-info/SOURCES.txt
percentum.egg-info/dependency_links.txt
percentum.egg-info/entry_points.txt
percentum.egg-info/top_level.txt