Metadata-Version: 2.1
Name: percentum
Version: 0.1
Summary: A CLI application for the percentage of the day.
Home-page: https://github.com/1darshanpatil/percentum
Author: Darshan P.
Author-email: drshnp@outlook.com
License: MIT
Project-URL: Documentation, https://github.com/1darshanpatil/percentum#readme
Project-URL: Source, https://github.com/1darshanpatil/percentum
Project-URL: Tracker, https://github.com/1darshanpatil/xpost/issues
Keywords: time,clock,hourglass,arena
Platform: UNKNOWN
Classifier: Development Status :: 4 - Beta
Classifier: Programming Language :: Python :: 3
Classifier: License :: OSI Approved :: MIT License
Classifier: Operating System :: OS Independent
Requires-Python: >=3.2
